{"sample": null, "protocol": "", "distance": 0.6, "reference_point": ["0", "0.4", "0"], "timestamps": {"ts1": -1108570545.0, "ts2": -1798053418.0, "ts3": -1777203121.0, "ts4": -1087719335.0}, "rssi": -90.59, "fp_power": -86.73, "fp_ampl2": 2179.0, "std_noise": 24.0, "temperature": 50.36}
{"sample": null, "protocol": "", "distance": 0.54, "reference_point": ["0", "0.4", "0"], "timestamps": {"ts1": -2090409393.0, "ts2": 1515167508.0, "ts3": 1535939151.0, "ts4": -2069636858.0}, "rssi": -90.59, "fp_power": -88.6, "fp_ampl2": 1869.0, "std_noise": 24.0, "temperature": 50.36}
{"sample": null, "protocol": "", "distance": 0.55, "reference_point": ["0", "0.4", "0"], "timestamps": {"ts1": -723434417.0, "ts2": -1477821329.0, "ts3": -1457037233.0, "ts4": -702647335.0}, "rssi": -91.31, "fp_power": -86.54, "fp_ampl2": 1946.0, "std_noise": 20.0, "temperature": 49.22}
{"sample": null, "protocol": "", "distance": 0.56, "reference_point": ["0", "0.4", "0"], "timestamps": {"ts1": 449469519.0, "ts2": -239770847.0, "ts3": -219019697.0, "ts4": 470221566.0}, "rssi": -89.49, "fp_power": -86.26, "fp_ampl2": 1985.0, "std_noise": 28.0, "temperature": 50.36}
{"sample": null, "protocol": "", "distance": 0.58, "reference_point": ["0", "0.4", "0"], "timestamps": {"ts1": 695435343.0, "ts2": 6283123.0, "ts3": 27188303.0, "ts4": 716341405.0}, "rssi": -90.95, "fp_power": -86.98, "fp_ampl2": 1906.0, "std_noise": 20.0, "temperature": 49.22}
{"sample": null, "protocol": "", "distance": 0.58, "reference_point": ["0", "0.4", "0"], "timestamps": {"ts1": -286479281.0, "ts2": -975539263.0, "ts3": -954688945.0, "ts4": -265628058.0}, "rssi": -90.52, "fp_power": -86.74, "fp_ampl2": 2137.0, "std_noise": 24.0, "temperature": 50.36}
{"sample": null, "protocol": "", "distance": 0.64, "reference_point": ["0", "0.4", "0"], "timestamps": {"ts1": 1080273487.0, "ts2": 327839069.0, "ts3": 348720719.0, "ts4": 1101158134.0}, "rssi": -89.78, "fp_power": -87.65, "fp_ampl2": 1863.0, "std_noise": 28.0, "temperature": 50.36}
{"sample": null, "protocol": "", "distance": 0.54, "reference_point": ["0", "0.4", "0"], "timestamps": {"ts1": 134941775.0, "ts2": -616946548.0, "ts3": -596118961.0, "ts4": 155772339.0}, "rssi": -90.59, "fp_power": -87.18, "fp_ampl2": 2141.0, "std_noise": 24.0, "temperature": 50.36}
{"sample": null, "protocol": "", "distance": 0.56, "reference_point": ["0", "0.4", "0"], "timestamps": {"ts1": -845664689.0, "ts2": -1597007166.0, "ts3": -1576133041.0, "ts4": -824787590.0}, "rssi": -90.87, "fp_power": -89.09, "fp_ampl2": 1716.0, "std_noise": 20.0, "temperature": 49.22}
{"sample": null, "protocol": "", "distance": 0.59, "reference_point": ["0", "0.4", "0"], "timestamps": {"ts1": -1829590961.0, "ts2": 1714579671.0, "ts3": 1735372879.0, "ts4": -1808794782.0}, "rssi": -90.3, "fp_power": -88.26, "fp_ampl2": 1916.0, "std_noise": 24.0, "temperature": 50.36}
{"sample": null, "protocol": "", "distance": 0.55, "reference_point": ["0", "0.4", "0"], "timestamps": {"ts1": 1488623183.0, "ts2": 738372414.0, "ts3": 759294543.0, "ts4": 1509548315.0}, "rssi": -89.92, "fp_power": -86.56, "fp_ampl2": 2163.0, "std_noise": 28.0, "temperature": 50.36}
{"sample": null, "protocol": "", "distance": 0.61, "reference_point": ["0", "0.4", "0"], "timestamps": {"ts1": 505525327.0, "ts2": -244179598.0, "ts3": -223376305.0, "ts4": 526331610.0}, "rssi": -89.99, "fp_power": -87.95, "fp_ampl2": 1934.0, "std_noise": 28.0, "temperature": 49.22}
{"sample": null, "protocol": "", "distance": 0.58, "reference_point": ["0", "0.4", "0"], "timestamps": {"ts1": -323975601.0, "ts2": -1073133445.0, "ts3": -1052360113.0, "ts4": -303199300.0}, "rssi": -91.1, "fp_power": -86.59, "fp_ampl2": 2088.0, "std_noise": 20.0, "temperature": 50.36}
{"sample": null, "protocol": "", "distance": 0.56, "reference_point": ["0", "0.4", "0"], "timestamps": {"ts1": -1265864625.0, "ts2": -2014476284.0, "ts3": -1993602481.0, "ts4": -1244987874.0}, "rssi": -91.02, "fp_power": -89.12, "fp_ampl2": 1679.0, "std_noise": 20.0, "temperature": 50.36}
{"sample": null, "protocol": "", "distance": 0.56, "reference_point": ["0", "0.4", "0"], "timestamps": {"ts1": -232901041.0, "ts2": -921129334.0, "ts3": -900207537.0, "ts4": -211978335.0}, "rssi": -90.87, "fp_power": -86.83, "fp_ampl2": 1946.0, "std_noise": 20.0, "temperature": 49.22}
{"sample": null, "protocol": "", "distance": 0.55, "reference_point": ["0", "0.4", "0"], "timestamps": {"ts1": -1637590449.0, "ts2": -765473049.0, "ts3": -744621489.0, "ts4": -1616738855.0}, "rssi": -90.59, "fp_power": -90.79, "fp_ampl2": 1522.0, "std_noise": 24.0, "temperature": 50.36}
{"sample": null, "protocol": "", "distance": 0.58, "reference_point": ["0", "0.4", "0"], "timestamps": {"ts1": 524520015.0, "ts2": -222865734.0, "ts3": -201984433.0, "ts4": 545404278.0}, "rssi": -90.95, "fp_power": -87.71, "fp_ampl2": 1945.0, "std_noise": 20.0, "temperature": 50.36}
{"sample": null, "protocol": "", "distance": 0.55, "reference_point": ["0", "0.4", "0"], "timestamps": {"ts1": -393503153.0, "ts2": -1140342462.0, "ts3": -1119459249.0, "ts4": -372616986.0}, "rssi": -90.08, "fp_power": -88.16, "fp_ampl2": 1884.0, "std_noise": 24.0, "temperature": 50.36}
{"sample": null, "protocol": "", "distance": 0.56, "reference_point": ["0", "0.4", "0"], "timestamps": {"ts1": -1311318449.0, "ts2": -2057611298.0, "ts3": -2036819377.0, "ts4": -1290523560.0}, "rssi": -90.95, "fp_power": -87.75, "fp_ampl2": 1748.0, "std_noise": 20.0, "temperature": 50.36}
{"sample": null, "protocol": "", "distance": 0.56, "reference_point": ["0", "0.4", "0"], "timestamps": {"ts1": -871618481.0, "ts2": 3750431.0, "ts3": 24676431.0, "ts4": -850692440.0}, "rssi": -90.87, "fp_power": -88.05, "fp_ampl2": 1756.0, "std_noise": 20.0, "temperature": 49.22}
{"sample": null, "protocol": "", "distance": 0.53, "reference_point": ["0", "0.4", "0"], "timestamps": {"ts1": -1966751665.0, "ts2": 1582782882.0, "ts3": 1603612751.0, "ts4": -1945918814.0}, "rssi": -90.59, "fp_power": -88.35, "fp_ampl2": 1827.0, "std_noise": 24.0, "temperature": 49.22}
{"sample": null, "protocol": "", "distance": 0.55, "reference_point": ["0", "0.4", "0"], "timestamps": {"ts1": 1346571343.0, "ts2": 601684512.0, "ts3": 622565455.0, "ts4": 1367455267.0}, "rssi": -91.02, "fp_power": -86.53, "fp_ampl2": 1963.0, "std_noise": 20.0, "temperature": 50.36}
{"sample": null, "protocol": "", "distance": 0.54, "reference_point": ["0", "0.4", "0"], "timestamps": {"ts1": 364881487.0, "ts2": -379459399.0, "ts3": -358593969.0, "ts4": 385749887.0}, "rssi": -91.02, "fp_power": -87.13, "fp_ampl2": 1846.0, "std_noise": 20.0, "temperature": 50.36}
{"sample": null, "protocol": "", "distance": 0.59, "reference_point": ["0", "0.4", "0"], "timestamps": {"ts1": -617068977.0, "ts2": -1360863854.0, "ts3": -1340088753.0, "ts4": -596290899.0}, "rssi": -90.23, "fp_power": -88.39, "fp_ampl2": 1891.0, "std_noise": 24.0, "temperature": 50.36}
{"sample": null, "protocol": "", "distance": 0.55, "reference_point": ["0", "0.4", "0"], "timestamps": {"ts1": -1599078321.0, "ts2": 1952640110.0, "ts3": 1973397071.0, "ts4": -1578318355.0}, "rssi": -90.59, "fp_power": -89.57, "fp_ampl2": 1671.0, "std_noise": 24.0, "temperature": 50.36}
{"sample": null, "protocol": "", "distance": 0.54, "reference_point": ["0", "0.4", "0"], "timestamps": {"ts1": 1714077263.0, "ts2": 971374405.0, "ts3": 992134223.0, "ts4": 1734840052.0}, "rssi": -90.87, "fp_power": -87.86, "fp_ampl2": 1912.0, "std_noise": 20.0, "temperature": 50.36}
{"sample": null, "protocol": "", "distance": 0.59, "reference_point": ["0", "0.4", "0"], "timestamps": {"ts1": 1493385295.0, "ts2": 806168655.0, "ts3": 826957391.0, "ts4": 1514174932.0}, "rssi": -91.38, "fp_power": -88.62, "fp_ampl2": 1882.0, "std_noise": 20.0, "temperature": 50.36}
{"sample": null, "protocol": "", "distance": 0.55, "reference_point": ["0", "0.4", "0"], "timestamps": {"ts1": -1476994481.0, "ts2": 2076386817.0, "ts3": 2097238095.0, "ts4": -1456140230.0}, "rssi": -90.08, "fp_power": -87.0, "fp_ampl2": 1962.0, "std_noise": 24.0, "temperature": 49.22}
{"sample": null, "protocol": "", "distance": 0.52, "reference_point": ["0", "0.4", "0"], "timestamps": {"ts1": -1231377329.0, "ts2": -1972441978.0, "ts3": -1951684529.0, "ts4": -1210616903.0}, "rssi": -90.95, "fp_power": -88.73, "fp_ampl2": 1800.0, "std_noise": 20.0, "temperature": 50.36}
{"sample": null, "protocol": "", "distance": 0.58, "reference_point": ["0", "0.4", "0"], "timestamps": {"ts1": 2081831503.0, "ts2": 1341312964.0, "ts3": 1362217039.0, "ts4": 2102738585.0}, "rssi": -90.16, "fp_power": -87.93, "fp_ampl2": 1911.0, "std_noise": 24.0, "temperature": 50.36}
{"sample": null, "protocol": "", "distance": 0.57, "reference_point": ["0", "0.4", "0"], "timestamps": {"ts1": 1859852367.0, "ts2": 1173009347.0, "ts3": 1193916495.0, "ts4": 1880760424.0}, "rssi": -91.1, "fp_power": -87.67, "fp_ampl2": 1974.0, "std_noise": 20.0, "temperature": 50.36}
{"sample": null, "protocol": "", "distance": 0.57, "reference_point": ["0", "0.4", "0"], "timestamps": {"ts1": 118110287.0, "ts2": -621316088.0, "ts3": -600495537.0, "ts4": 138933803.0}, "rssi": -90.3, "fp_power": -88.7, "fp_ampl2": 1815.0, "std_noise": 24.0, "temperature": 50.36}
{"sample": null, "protocol": "", "distance": 0.52, "reference_point": ["0", "0.4", "0"], "timestamps": {"ts1": -863442353.0, "ts2": -1602322661.0, "ts3": -1581417905.0, "ts4": -842534629.0}, "rssi": -90.16, "fp_power": -88.4, "fp_ampl2": 1811.0, "std_noise": 24.0, "temperature": 50.36}
{"sample": null, "protocol": "", "distance": 0.59, "reference_point": ["0", "0.4", "0"], "timestamps": {"ts1": -1845444529.0, "ts2": 1711188542.0, "ts3": 1732038735.0, "ts4": -1824591329.0}, "rssi": -90.16, "fp_power": -88.92, "fp_ampl2": 1748.0, "std_noise": 24.0, "temperature": 49.22}
{"sample": null, "protocol": "", "distance": 0.56, "reference_point": ["0", "0.4", "0"], "timestamps": {"ts1": -2066797489.0, "ts2": 1541700789.0, "ts3": 1562539599.0, "ts4": -2045957780.0}, "rssi": -90.16, "fp_power": -86.98, "fp_ampl2": 2023.0, "std_noise": 24.0, "temperature": 50.36}
{"sample": null, "protocol": "", "distance": 0.56, "reference_point": ["0", "0.4", "0"], "timestamps": {"ts1": 486094927.0, "ts2": -251147164.0, "ts3": -230309297.0, "ts4": 506935776.0}, "rssi": -90.59, "fp_power": -86.97, "fp_ampl2": 2139.0, "std_noise": 24.0, "temperature": 50.36}
{"sample": null, "protocol": "", "distance": 0.6, "reference_point": ["0", "0.4", "0"], "timestamps": {"ts1": 261148239.0, "ts2": -425133678.0, "ts3": -404231089.0, "ts4": 282051724.0}, "rssi": -90.08, "fp_power": -87.73, "fp_ampl2": 1932.0, "std_noise": 24.0, "temperature": 50.36}
{"sample": null, "protocol": "", "distance": 0.58, "reference_point": ["0", "0.4", "0"], "timestamps": {"ts1": -1477651377.0, "ts2": 2081165859.0, "ts3": 2102048847.0, "ts4": -1456765417.0}, "rssi": -90.16, "fp_power": -88.26, "fp_ampl2": 1741.0, "std_noise": 24.0, "temperature": 50.36}
{"sample": null, "protocol": "", "distance": 0.55, "reference_point": ["0", "0.4", "0"], "timestamps": {"ts1": 1835553359.0, "ts2": 1099949322.0, "ts3": 1120737871.0, "ts4": 1856344875.0}, "rssi": -91.31, "fp_power": -86.5, "fp_ampl2": 2136.0, "std_noise": 20.0, "temperature": 50.36}
{"sample": null, "protocol": "", "distance": 0.59, "reference_point": ["0", "0.4", "0"], "timestamps": {"ts1": 853625423.0, "ts2": 118567369.0, "ts3": 139344463.0, "ts4": 874405482.0}, "rssi": -89.56, "fp_power": -87.62, "fp_ampl2": 1979.0, "std_noise": 28.0, "temperature": 50.36}
{"sample": null, "protocol": "", "distance": 0.54, "reference_point": ["0", "0.4", "0"], "timestamps": {"ts1": -128059825.0, "ts2": -862571890.0, "ts3": -841811889.0, "ts4": -107296831.0}, "rssi": -90.52, "fp_power": -86.26, "fp_ampl2": 2049.0, "std_noise": 24.0, "temperature": 50.36}
{"sample": null, "protocol": "", "distance": 0.56, "reference_point": ["0", "0.4", "0"], "timestamps": {"ts1": -1109910449.0, "ts2": -1843876553.0, "ts3": -1822973361.0, "ts4": -1089004287.0}, "rssi": -90.59, "fp_power": -87.05, "fp_ampl2": 2118.0, "std_noise": 24.0, "temperature": 50.36}
{"sample": null, "protocol": "", "distance": 0.59, "reference_point": ["0", "0.4", "0"], "timestamps": {"ts1": -2091771313.0, "ts2": 1469775796.0, "ts3": 1490563151.0, "ts4": -2070980966.0}, "rssi": -90.08, "fp_power": -87.19, "fp_ampl2": 1975.0, "std_noise": 24.0, "temperature": 50.36}
{"sample": null, "protocol": "", "distance": 0.57, "reference_point": ["0", "0.4", "0"], "timestamps": {"ts1": 1980400207.0, "ts2": 1294772815.0, "ts3": 1315677775.0, "ts4": 2001306064.0}, "rssi": -90.66, "fp_power": -87.43, "fp_ampl2": 1991.0, "std_noise": 24.0, "temperature": 50.36}
{"sample": null, "protocol": "", "distance": 0.59, "reference_point": ["0", "0.4", "0"], "timestamps": {"ts1": -987990961.0, "ts2": -1720294563.0, "ts3": -1699422641.0, "ts4": -967116054.0}, "rssi": -90.16, "fp_power": -87.55, "fp_ampl2": 1964.0, "std_noise": 24.0, "temperature": 50.36}
{"sample": null, "protocol": "", "distance": 0.56, "reference_point": ["0", "0.4", "0"], "timestamps": {"ts1": -742314929.0, "ts2": -1474097379.0, "ts3": -1453329841.0, "ts4": -721544445.0}, "rssi": -90.23, "fp_power": -86.59, "fp_ampl2": 2064.0, "std_noise": 24.0, "temperature": 50.36}
{"sample": null, "protocol": "", "distance": 0.55, "reference_point": ["0", "0.4", "0"], "timestamps": {"ts1": -1723936177.0, "ts2": 1839794578.0, "ts3": 1860587599.0, "ts4": -1703140173.0}, "rssi": -90.95, "fp_power": -86.94, "fp_ampl2": 1874.0, "std_noise": 20.0, "temperature": 50.36}
{"sample": null, "protocol": "", "distance": 0.56, "reference_point": ["0", "0.4", "0"], "timestamps": {"ts1": 1589063247.0, "ts2": 858372564.0, "ts3": 879058511.0, "ts4": 1609752201.0}, "rssi": -91.31, "fp_power": -89.15, "fp_ampl2": 1744.0, "std_noise": 20.0, "temperature": 50.36}
{"sample": null, "protocol": "", "distance": 0.58, "reference_point": ["0", "0.4", "0"], "timestamps": {"ts1": 607241807.0, "ts2": -122903095.0, "ts3": -102114225.0, "ts4": 628033648.0}, "rssi": -89.92, "fp_power": -88.09, "fp_ampl2": 1863.0, "std_noise": 28.0, "temperature": 50.36}
{"sample": null, "protocol": "", "distance": 0.58, "reference_point": ["0", "0.4", "0"], "timestamps": {"ts1": -374347697.0, "ts2": -1103946847.0, "ts3": -1083153329.0, "ts4": -353551222.0}, "rssi": -91.17, "fp_power": -86.24, "fp_ampl2": 2062.0, "std_noise": 20.0, "temperature": 50.36}
{"sample": null, "protocol": "", "distance": 0.57, "reference_point": ["0", "0.4", "0"], "timestamps": {"ts1": -1308081585.0, "ts2": -2037134588.0, "ts3": -2016414129.0, "ts4": -1287358151.0}, "rssi": -90.3, "fp_power": -87.49, "fp_ampl2": 1989.0, "std_noise": 24.0, "temperature": 50.36}
{"sample": null, "protocol": "", "distance": 0.53, "reference_point": ["0", "0.4", "0"], "timestamps": {"ts1": 2070323279.0, "ts2": 1341816544.0, "ts3": 1362584655.0, "ts4": 2091094370.0}, "rssi": -90.38, "fp_power": -88.8, "fp_ampl2": 1708.0, "std_noise": 24.0, "temperature": 50.36}
{"sample": null, "protocol": "", "distance": 0.55, "reference_point": ["0", "0.4", "0"], "timestamps": {"ts1": 1151002191.0, "ts2": 423041686.0, "ts3": 443860047.0, "ts4": 1171823530.0}, "rssi": -89.92, "fp_power": -86.86, "fp_ampl2": 2089.0, "std_noise": 28.0, "temperature": 50.36}
{"sample": null, "protocol": "", "distance": 0.54, "reference_point": ["0", "0.4", "0"], "timestamps": {"ts1": 1505123919.0, "ts2": -1884371169.0, "ts3": -1863612337.0, "ts4": 1525882780.0}, "rssi": -90.23, "fp_power": -87.26, "fp_ampl2": 2015.0, "std_noise": 24.0, "temperature": 50.36}
{"sample": null, "protocol": "", "distance": 0.55, "reference_point": ["0", "0.4", "0"], "timestamps": {"ts1": 703350351.0, "ts2": -23748713.0, "ts3": -2842033.0, "ts4": 724260013.0}, "rssi": -90.16, "fp_power": -87.41, "fp_ampl2": 1990.0, "std_noise": 24.0, "temperature": 50.36}
{"sample": null, "protocol": "", "distance": 0.54, "reference_point": ["0", "0.4", "0"], "timestamps": {"ts1": -234183089.0, "ts2": -960736116.0, "ts3": -939867057.0, "ts4": -213311049.0}, "rssi": -90.95, "fp_power": -88.25, "fp_ampl2": 1889.0, "std_noise": 20.0, "temperature": 50.36}
{"sample": null, "protocol": "", "distance": 0.51, "reference_point": ["0", "0.4", "0"], "timestamps": {"ts1": 1025624143.0, "ts2": 341131541.0, "ts3": 362026575.0, "ts4": 1046520075.0}, "rssi": -90.3, "fp_power": -87.99, "fp_ampl2": 1943.0, "std_noise": 24.0, "temperature": 50.36}
{"sample": null, "protocol": "", "distance": 0.52, "reference_point": ["0", "0.4", "0"], "timestamps": {"ts1": -678474161.0, "ts2": -1404165832.0, "ts3": -1383266737.0, "ts4": -657572093.0}, "rssi": -90.87, "fp_power": -86.22, "fp_ampl2": 2034.0, "std_noise": 20.0, "temperature": 50.36}
{"sample": null, "protocol": "", "distance": 0.55, "reference_point": ["0", "0.4", "0"], "timestamps": {"ts1": -1660378545.0, "ts2": 1909442693.0, "ts3": 1930256975.0, "ts4": -1639561306.0}, "rssi": -90.3, "fp_power": -87.18, "fp_ampl2": 2047.0, "std_noise": 24.0, "temperature": 50.36}
{"sample": null, "protocol": "", "distance": 0.63, "reference_point": ["0", "0.4", "0"], "timestamps": {"ts1": -1175414193.0, "ts2": -265319185.0, "ts3": -244395441.0, "ts4": -1154490375.0}, "rssi": -90.3, "fp_power": -87.12, "fp_ampl2": 2052.0, "std_noise": 24.0, "temperature": 50.36}
{"sample": null, "protocol": "", "distance": 0.54, "reference_point": ["0", "0.4", "0"], "timestamps": {"ts1": 1773064271.0, "ts2": 1088909461.0, "ts3": 1109730895.0, "ts4": 1793886605.0}, "rssi": -90.87, "fp_power": -86.99, "fp_ampl2": 1840.0, "std_noise": 20.0, "temperature": 50.36}
{"sample": null, "protocol": "", "distance": 0.53, "reference_point": ["0", "0.4", "0"], "timestamps": {"ts1": 956452431.0, "ts2": 272355578.0, "ts3": 293269071.0, "ts4": 977366821.0}, "rssi": -90.16, "fp_power": -86.96, "fp_ampl2": 2042.0, "std_noise": 24.0, "temperature": 50.36}
{"sample": null, "protocol": "", "distance": 0.58, "reference_point": ["0", "0.4", "0"], "timestamps": {"ts1": 23402063.0, "ts2": -660601525.0, "ts3": -639729585.0, "ts4": 44274905.0}, "rssi": -91.24, "fp_power": -88.51, "fp_ampl2": 1875.0, "std_noise": 20.0, "temperature": 50.36}
{"sample": null, "protocol": "", "distance": 0.55, "reference_point": ["0", "0.4", "0"], "timestamps": {"ts1": -734777777.0, "ts2": -1418723345.0, "ts3": -1397801905.0, "ts4": -713855436.0}, "rssi": -90.59, "fp_power": -86.63, "fp_ampl2": 2139.0, "std_noise": 24.0, "temperature": 50.36}
{"sample": null, "protocol": "", "distance": 0.6, "reference_point": ["0", "0.4", "0"], "timestamps": {"ts1": -1668586417.0, "ts2": 1942528505.0, "ts3": 1963288143.0, "ts4": -1647825873.0}, "rssi": -90.16, "fp_power": -87.88, "fp_ampl2": 1739.0, "std_noise": 24.0, "temperature": 49.22}
{"sample": null, "protocol": "", "distance": 0.56, "reference_point": ["0", "0.4", "0"], "timestamps": {"ts1": 810106959.0, "ts2": 88163342.0, "ts3": 109063247.0, "ts4": 831009841.0}, "rssi": -89.78, "fp_power": -88.26, "fp_ampl2": 1931.0, "std_noise": 28.0, "temperature": 50.36}
{"sample": null, "protocol": "", "distance": 0.55, "reference_point": ["0", "0.4", "0"], "timestamps": {"ts1": 991881807.0, "ts2": 270458486.0, "ts3": 291243087.0, "ts4": 1012669406.0}, "rssi": -92.14, "fp_power": -89.09, "fp_ampl2": 1720.0, "std_noise": 16.0, "temperature": 50.36}
{"sample": null, "protocol": "", "distance": 0.55, "reference_point": ["0", "0.4", "0"], "timestamps": {"ts1": 282325583.0, "ts2": -438757623.0, "ts3": -417833393.0, "ts4": 303252773.0}, "rssi": -91.02, "fp_power": -87.64, "fp_ampl2": 1979.0, "std_noise": 20.0, "temperature": 48.08}
{"sample": null, "protocol": "", "distance": 0.58, "reference_point": ["0", "0.4", "0"], "timestamps": {"ts1": 400377935.0, "ts2": -320185532.0, "ts3": -299302321.0, "ts4": 421264107.0}, "rssi": -89.71, "fp_power": -86.74, "fp_ampl2": 2006.0, "std_noise": 28.0, "temperature": 49.22}
{"sample": null, "protocol": "", "distance": 0.53, "reference_point": ["0", "0.4", "0"], "timestamps": {"ts1": 304966735.0, "ts2": -378464536.0, "ts3": -357603761.0, "ts4": 325828411.0}, "rssi": -89.99, "fp_power": -86.93, "fp_ampl2": 2153.0, "std_noise": 28.0, "temperature": 49.22}
{"sample": null, "protocol": "", "distance": 0.6, "reference_point": ["0", "0.4", "0"], "timestamps": {"ts1": -1499455409.0, "ts2": 2076039879.0, "ts3": 2096852047.0, "ts4": -1478640257.0}, "rssi": -90.59, "fp_power": -86.92, "fp_ampl2": 2017.0, "std_noise": 24.0, "temperature": 50.36}
{"sample": null, "protocol": "", "distance": 0.57, "reference_point": ["0", "0.4", "0"], "timestamps": {"ts1": 1852167759.0, "ts2": 1133241529.0, "ts3": 1154148431.0, "ts4": 1873077661.0}, "rssi": -90.95, "fp_power": -86.71, "fp_ampl2": 1954.0, "std_noise": 20.0, "temperature": 50.36}
{"sample": null, "protocol": "", "distance": 0.58, "reference_point": ["0", "0.4", "0"], "timestamps": {"ts1": -1239756721.0, "ts2": -1922949158.0, "ts3": -1902077361.0, "ts4": -1218884020.0}, "rssi": -91.1, "fp_power": -86.28, "fp_ampl2": 2116.0, "std_noise": 20.0, "temperature": 49.22}
{"sample": null, "protocol": "", "distance": 0.52, "reference_point": ["0", "0.4", "0"], "timestamps": {"ts1": 1286313039.0, "ts2": 568246814.0, "ts3": 589160527.0, "ts4": 1307229724.0}, "rssi": -90.95, "fp_power": -86.52, "fp_ampl2": 2033.0, "std_noise": 20.0, "temperature": 50.36}
{"sample": null, "protocol": "", "distance": 0.56, "reference_point": ["0", "0.4", "0"], "timestamps": {"ts1": 1129025615.0, "ts2": 446018315.0, "ts3": 466926159.0, "ts4": 1149934358.0}, "rssi": -91.24, "fp_power": -86.7, "fp_ampl2": 1970.0, "std_noise": 20.0, "temperature": 49.22}
{"sample": null, "protocol": "", "distance": 0.54, "reference_point": ["0", "0.4", "0"], "timestamps": {"ts1": 1609811535.0, "ts2": 926857683.0, "ts3": 947641423.0, "ts4": 1630596173.0}, "rssi": -90.59, "fp_power": -87.35, "fp_ampl2": 2122.0, "std_noise": 24.0, "temperature": 50.36}
{"sample": null, "protocol": "", "distance": 0.59, "reference_point": ["0", "0.4", "0"], "timestamps": {"ts1": -95364529.0, "ts2": -812024015.0, "ts3": -791236017.0, "ts4": -74573581.0}, "rssi": -89.78, "fp_power": -87.54, "fp_ampl2": 1979.0, "std_noise": 28.0, "temperature": 50.36}
{"sample": null, "protocol": "", "distance": 0.51, "reference_point": ["0", "0.4", "0"], "timestamps": {"ts1": -1037438897.0, "ts2": -1753552674.0, "ts3": -1732700593.0, "ts4": -1016583837.0}, "rssi": -91.38, "fp_power": -86.58, "fp_ampl2": 2135.0, "std_noise": 20.0, "temperature": 50.36}
{"sample": null, "protocol": "", "distance": 0.58, "reference_point": ["0", "0.4", "0"], "timestamps": {"ts1": -627781553.0, "ts2": 297141778.0, "ts3": 318049871.0, "ts4": -606873418.0}, "rssi": -90.38, "fp_power": -86.33, "fp_ampl2": 2022.0, "std_noise": 24.0, "temperature": 50.36}
{"sample": null, "protocol": "", "distance": 0.55, "reference_point": ["0", "0.4", "0"], "timestamps": {"ts1": -1476951473.0, "ts2": 2102762980.0, "ts3": 2123521615.0, "ts4": -1456189849.0}, "rssi": -90.08, "fp_power": -87.48, "fp_ampl2": 1968.0, "std_noise": 24.0, "temperature": 50.36}
{"sample": null, "protocol": "", "distance": 0.56, "reference_point": ["0", "0.4", "0"], "timestamps": {"ts1": -1700655025.0, "ts2": 1911781220.0, "ts3": 1932662863.0, "ts4": -1679772486.0}, "rssi": -90.08, "fp_power": -87.47, "fp_ampl2": 1779.0, "std_noise": 24.0, "temperature": 50.36}
{"sample": null, "protocol": "", "distance": 0.6, "reference_point": ["0", "0.4", "0"], "timestamps": {"ts1": -2076877745.0, "ts2": -1149645416.0, "ts3": -1128795057.0, "ts4": -2056027328.0}, "rssi": -92.06, "fp_power": -87.84, "fp_ampl2": 1982.0, "std_noise": 16.0, "temperature": 50.36}
{"sample": null, "protocol": "", "distance": 0.6, "reference_point": ["0", "0.4", "0"], "timestamps": {"ts1": -954902961.0, "ts2": -1668699385.0, "ts3": -1647931825.0, "ts4": -934132438.0}, "rssi": -89.85, "fp_power": -87.05, "fp_ampl2": 2080.0, "std_noise": 28.0, "temperature": 49.22}
{"sample": null, "protocol": "", "distance": 0.59, "reference_point": ["0", "0.4", "0"], "timestamps": {"ts1": -773128625.0, "ts2": -1486404981.0, "ts3": -1465615281.0, "ts4": -752336274.0}, "rssi": -90.08, "fp_power": -90.68, "fp_ampl2": 1440.0, "std_noise": 24.0, "temperature": 50.36}
{"sample": null, "protocol": "", "distance": 0.55, "reference_point": ["0", "0.4", "0"], "timestamps": {"ts1": -1714508721.0, "ts2": 1867727823.0, "ts3": 1888486991.0, "ts4": -1693746572.0}, "rssi": -91.31, "fp_power": -88.43, "fp_ampl2": 1945.0, "std_noise": 20.0, "temperature": 50.36}
{"sample": null, "protocol": "", "distance": 0.56, "reference_point": ["0", "0.4", "0"], "timestamps": {"ts1": -448776113.0, "ts2": -1130920336.0, "ts3": -1110065073.0, "ts4": -427919941.0}, "rssi": -90.08, "fp_power": -88.59, "fp_ampl2": 1809.0, "std_noise": 24.0, "temperature": 50.36}
{"sample": null, "protocol": "", "distance": 0.52, "reference_point": ["0", "0.4", "0"], "timestamps": {"ts1": 2140375119.0, "ts2": 1428505159.0, "ts3": 1449353807.0, "ts4": -2133740546.0}, "rssi": -91.24, "fp_power": -86.66, "fp_ampl2": 1969.0, "std_noise": 20.0, "temperature": 50.36}
{"sample": null, "protocol": "", "distance": 0.59, "reference_point": ["0", "0.4", "0"], "timestamps": {"ts1": 1209592911.0, "ts2": 498268595.0, "ts3": 519041615.0, "ts4": 1230368878.0}, "rssi": -90.45, "fp_power": -86.3, "fp_ampl2": 2096.0, "std_noise": 24.0, "temperature": 49.22}
{"sample": null, "protocol": "", "distance": 0.59, "reference_point": ["0", "0.4", "0"], "timestamps": {"ts1": 287197775.0, "ts2": -423580840.0, "ts3": -402654641.0, "ts4": 308126947.0}, "rssi": -91.31, "fp_power": -87.11, "fp_ampl2": 2061.0, "std_noise": 20.0, "temperature": 50.36}
{"sample": null, "protocol": "", "distance": 0.58, "reference_point": ["0", "0.4", "0"], "timestamps": {"ts1": 354179151.0, "ts2": -327631885.0, "ts3": -306880433.0, "ts4": 374931502.0}, "rssi": -90.23, "fp_power": -87.48, "fp_ampl2": 1888.0, "std_noise": 24.0, "temperature": 50.36}
{"sample": null, "protocol": "", "distance": 0.57, "reference_point": ["0", "0.4", "0"], "timestamps": {"ts1": -624233393.0, "ts2": -1305952610.0, "ts3": -1285126065.0, "ts4": -603405951.0}, "rssi": -90.08, "fp_power": -86.38, "fp_ampl2": 1975.0, "std_noise": 24.0, "temperature": 50.36}
{"sample": null, "protocol": "", "distance": 0.55, "reference_point": ["0", "0.4", "0"], "timestamps": {"ts1": -1607398833.0, "ts2": 2005941047.0, "ts3": 2026821711.0, "ts4": -1586517273.0}, "rssi": -90.87, "fp_power": -87.38, "fp_ampl2": 1743.0, "std_noise": 20.0, "temperature": 50.36}
{"sample": null, "protocol": "", "distance": 0.61, "reference_point": ["0", "0.4", "0"], "timestamps": {"ts1": 1008486479.0, "ts2": 299683954.0, "ts3": 320590415.0, "ts4": 1029395932.0}, "rssi": -91.1, "fp_power": -87.21, "fp_ampl2": 2048.0, "std_noise": 20.0, "temperature": 50.36}
{"sample": null, "protocol": "", "distance": 0.57, "reference_point": ["0", "0.4", "0"], "timestamps": {"ts1": 1190201935.0, "ts2": 481919355.0, "ts3": 502692431.0, "ts4": 1210977971.0}, "rssi": -89.85, "fp_power": -87.89, "fp_ampl2": 2000.0, "std_noise": 28.0, "temperature": 50.36}
{"sample": null, "protocol": "", "distance": 0.55, "reference_point": ["0", "0.4", "0"], "timestamps": {"ts1": 248209487.0, "ts2": -459527596.0, "ts3": -438701489.0, "ts4": 269038578.0}, "rssi": -91.24, "fp_power": -88.33, "fp_ampl2": 1942.0, "std_noise": 20.0, "temperature": 50.36}
{"sample": null, "protocol": "", "distance": 0.54, "reference_point": ["0", "0.4", "0"], "timestamps": {"ts1": 1515189839.0, "ts2": 833886709.0, "ts3": 854686287.0, "ts4": 1535990323.0}, "rssi": -90.08, "fp_power": -90.39, "fp_ampl2": 1487.0, "std_noise": 24.0, "temperature": 50.36}
{"sample": null, "protocol": "", "distance": 0.57, "reference_point": ["0", "0.4", "0"], "timestamps": {"ts1": -191413681.0, "ts2": -898290217.0, "ts3": -877697457.0, "ts4": -170817941.0}, "rssi": -91.31, "fp_power": -87.93, "fp_ampl2": 2026.0, "std_noise": 20.0, "temperature": 50.36}
{"sample": null, "protocol": "", "distance": 0.52, "reference_point": ["0", "0.4", "0"], "timestamps": {"ts1": -1134748593.0, "ts2": -1841079736.0, "ts3": -1820241329.0, "ts4": -1113907228.0}, "rssi": -90.16, "fp_power": -88.58, "fp_ampl2": 1837.0, "std_noise": 24.0, "temperature": 50.36}
{"sample": null, "protocol": "", "distance": 0.6, "reference_point": ["0", "0.4", "0"], "timestamps": {"ts1": 69890639.0, "ts2": -611175941.0, "ts3": -590325681.0, "ts4": 90741803.0}, "rssi": -90.95, "fp_power": -87.71, "fp_ampl2": 1963.0, "std_noise": 20.0, "temperature": 50.36}
{"sample": null, "protocol": "", "distance": 0.58, "reference_point": ["0", "0.4", "0"], "timestamps": {"ts1": -1636906417.0, "ts2": 1952589692.0, "ts3": 1973469263.0, "ts4": -1616023888.0}, "rssi": -90.52, "fp_power": -88.07, "fp_ampl2": 2001.0, "std_noise": 24.0, "temperature": 50.36}
{"sample": null, "protocol": "", "distance": 0.54, "reference_point": ["0", "0.4", "0"], "timestamps": {"ts1": 1713624143.0, "ts2": 1008698294.0, "ts3": 1029482575.0, "ts4": 1734411399.0}, "rssi": -90.52, "fp_power": -87.24, "fp_ampl2": 2052.0, "std_noise": 24.0, "temperature": 49.22}
{"sample": null, "protocol": "", "distance": 0.61, "reference_point": ["0", "0.4", "0"], "timestamps": {"ts1": 2117989967.0, "ts2": -1233683744.0, "ts3": -1212877233.0, "ts4": 2138796549.0}, "rssi": -89.49, "fp_power": -87.47, "fp_ampl2": 1984.0, "std_noise": 28.0, "temperature": 50.36}
{"sample": null, "protocol": "", "distance": 0.6, "reference_point": ["0", "0.4", "0"], "timestamps": {"ts1": 1212682831.0, "ts2": 508616921.0, "ts3": 529427535.0, "ts4": 1233496412.0}, "rssi": -91.38, "fp_power": -87.51, "fp_ampl2": 1926.0, "std_noise": 20.0, "temperature": 50.36}
{"sample": null, "protocol": "", "distance": 0.61, "reference_point": ["0", "0.4", "0"], "timestamps": {"ts1": 271007311.0, "ts2": -432513245.0, "ts3": -411650993.0, "ts4": 291872548.0}, "rssi": -89.78, "fp_power": -87.07, "fp_ampl2": 1997.0, "std_noise": 28.0, "temperature": 50.36}
{"sample": null, "protocol": "", "distance": 0.54, "reference_point": ["0", "0.4", "0"], "timestamps": {"ts1": 1538165327.0, "ts2": 857571828.0, "ts3": 878323791.0, "ts4": 1558918201.0}, "rssi": -90.45, "fp_power": -89.11, "fp_ampl2": 1680.0, "std_noise": 24.0, "temperature": 50.36}
{"sample": null, "protocol": "", "distance": 0.56, "reference_point": ["0", "0.4", "0"], "timestamps": {"ts1": 596886095.0, "ts2": -83615634.0, "ts3": -62733745.0, "ts4": 617768886.0}, "rssi": -89.85, "fp_power": -86.54, "fp_ampl2": 1953.0, "std_noise": 28.0, "temperature": 49.22}
{"sample": null, "protocol": "", "distance": 0.59, "reference_point": ["0", "0.4", "0"], "timestamps": {"ts1": 209505359.0, "ts2": 1156518416.0, "ts3": 1177428047.0, "ts4": 230415048.0}, "rssi": -90.95, "fp_power": -88.55, "fp_ampl2": 1835.0, "std_noise": 20.0, "temperature": 50.36}
{"sample": null, "protocol": "", "distance": 0.57, "reference_point": ["0", "0.4", "0"], "timestamps": {"ts1": -1090811313.0, "ts2": -1771164098.0, "ts3": -1750326193.0, "ts4": -1069972514.0}, "rssi": -90.52, "fp_power": -87.44, "fp_ampl2": 2067.0, "std_noise": 24.0, "temperature": 49.22}
{"sample": null, "protocol": "", "distance": 0.58, "reference_point": ["0", "0.4", "0"], "timestamps": {"ts1": 1452931663.0, "ts2": 751701200.0, "ts3": 772605519.0, "ts4": 1473838957.0}, "rssi": -91.24, "fp_power": -86.63, "fp_ampl2": 2071.0, "std_noise": 20.0, "temperature": 50.36}
{"sample": null, "protocol": "", "distance": 0.57, "reference_point": ["0", "0.4", "0"], "timestamps": {"ts1": -1756705201.0, "ts2": 1858088703.0, "ts3": 1878839887.0, "ts4": -1735953122.0}, "rssi": -91.31, "fp_power": -86.4, "fp_ampl2": 2031.0, "std_noise": 20.0, "temperature": 50.36}
{"sample": null, "protocol": "", "distance": 0.58, "reference_point": ["0", "0.4", "0"], "timestamps": {"ts1": 716988495.0, "ts2": 16822917.0, "ts3": 37727311.0, "ts4": 737895552.0}, "rssi": -90.08, "fp_power": -87.49, "fp_ampl2": 1947.0, "std_noise": 24.0, "temperature": 50.36}
{"sample": null, "protocol": "", "distance": 0.6, "reference_point": ["0", "0.4", "0"], "timestamps": {"ts1": -221454257.0, "ts2": -921074232.0, "ts3": -900422577.0, "ts4": -200799629.0}, "rssi": -90.16, "fp_power": -86.59, "fp_ampl2": 1903.0, "std_noise": 24.0, "temperature": 50.36}
{"sample": null, "protocol": "", "distance": 0.55, "reference_point": ["0", "0.4", "0"], "timestamps": {"ts1": 1042945103.0, "ts2": 363008292.0, "ts3": 383878735.0, "ts4": 1063816446.0}, "rssi": -90.23, "fp_power": -87.71, "fp_ampl2": 1966.0, "std_noise": 24.0, "temperature": 48.08}
{"sample": null, "protocol": "", "distance": 0.58, "reference_point": ["0", "0.4", "0"], "timestamps": {"ts1": -1181411761.0, "ts2": -1861252654.0, "ts3": -1840349105.0, "ts4": -1160507305.0}, "rssi": -90.16, "fp_power": -88.31, "fp_ampl2": 1819.0, "std_noise": 24.0, "temperature": 49.22}
{"sample": null, "protocol": "", "distance": 0.54, "reference_point": ["0", "0.4", "0"], "timestamps": {"ts1": 1356990031.0, "ts2": 658790847.0, "ts3": 679558223.0, "ts4": 1377760401.0}, "rssi": -90.16, "fp_power": -89.41, "fp_ampl2": 1672.0, "std_noise": 24.0, "temperature": 49.22}
{"sample": null, "protocol": "", "distance": 0.54, "reference_point": ["0", "0.4", "0"], "timestamps": {"ts1": -1693863857.0, "ts2": 1921407320.0, "ts3": 1942174287.0, "ts4": -1673095988.0}, "rssi": -90.08, "fp_power": -88.35, "fp_ampl2": 1804.0, "std_noise": 24.0, "temperature": 49.22}
{"sample": null, "protocol": "", "distance": 0.54, "reference_point": ["0", "0.4", "0"], "timestamps": {"ts1": 829201487.0, "ts2": 131858616.0, "ts3": 152618575.0, "ts4": 849964424.0}, "rssi": -90.95, "fp_power": -86.85, "fp_ampl2": 2032.0, "std_noise": 20.0, "temperature": 50.36}
{"sample": null, "protocol": "", "distance": 0.56, "reference_point": ["0", "0.4", "0"], "timestamps": {"ts1": 677217871.0, "ts2": -2294626.0, "ts3": 18482255.0, "ts4": 697995646.0}, "rssi": -90.59, "fp_power": -86.51, "fp_ampl2": 2185.0, "std_noise": 24.0, "temperature": 50.36}
{"sample": null, "protocol": "", "distance": 0.54, "reference_point": ["0", "0.4", "0"], "timestamps": {"ts1": 1155942991.0, "ts2": 476483534.0, "ts3": 497390671.0, "ts4": 1176851030.0}, "rssi": -90.3, "fp_power": -88.31, "fp_ampl2": 1909.0, "std_noise": 24.0, "temperature": 50.36}
{"sample": null, "protocol": "", "distance": 0.58, "reference_point": ["0", "0.4", "0"], "timestamps": {"ts1": 210778703.0, "ts2": -468588946.0, "ts3": -447727025.0, "ts4": 231641522.0}, "rssi": -90.52, "fp_power": -86.76, "fp_ampl2": 2103.0, "std_noise": 24.0, "temperature": 50.36}
{"sample": null, "protocol": "", "distance": 0.54, "reference_point": ["0", "0.4", "0"], "timestamps": {"ts1": -1534010289.0, "ts2": 2065559153.0, "ts3": 2086350927.0, "ts4": -1513215519.0}, "rssi": -91.02, "fp_power": -87.82, "fp_ampl2": 1934.0, "std_noise": 20.0, "temperature": 50.36}
{"sample": null, "protocol": "", "distance": 0.57, "reference_point": ["0", "0.4", "0"], "timestamps": {"ts1": -1479896497.0, "ts2": 2135846246.0, "ts3": -2138272689.0, "ts4": -1459047237.0}, "rssi": -90.23, "fp_power": -87.38, "fp_ampl2": 1998.0, "std_noise": 24.0, "temperature": 48.08}
{"sample": null, "protocol": "", "distance": 0.55, "reference_point": ["0", "0.4", "0"], "timestamps": {"ts1": 862559823.0, "ts2": 168042835.0, "ts3": 188956239.0, "ts4": 883476199.0}, "rssi": -90.87, "fp_power": -87.09, "fp_ampl2": 1978.0, "std_noise": 20.0, "temperature": 49.22}
{"sample": null, "protocol": "", "distance": 0.59, "reference_point": ["0", "0.4", "0"], "timestamps": {"ts1": -56736177.0, "ts2": -750708994.0, "ts3": -729803697.0, "ts4": -35827901.0}, "rssi": -90.38, "fp_power": -88.01, "fp_ampl2": 1957.0, "std_noise": 24.0, "temperature": 50.36}
{"sample": null, "protocol": "", "distance": 0.57, "reference_point": ["0", "0.4", "0"], "timestamps": {"ts1": 77952079.0, "ts2": -615502545.0, "ts3": -594621873.0, "ts4": 98835733.0}, "rssi": -91.24, "fp_power": -88.4, "fp_ampl2": 1909.0, "std_noise": 20.0, "temperature": 49.22}
{"sample": null, "protocol": "", "distance": 0.58, "reference_point": ["0", "0.4", "0"], "timestamps": {"ts1": -567608241.0, "ts2": -1260723294.0, "ts3": -1239916977.0, "ts4": -546798940.0}, "rssi": -90.52, "fp_power": -88.84, "fp_ampl2": 1765.0, "std_noise": 24.0, "temperature": 49.22}
{"sample": null, "protocol": "", "distance": 0.56, "reference_point": ["0", "0.4", "0"], "timestamps": {"ts1": 677354063.0, "ts2": -1497805.0, "ts3": 19363407.0, "ts4": 698216176.0}, "rssi": -91.17, "fp_power": -88.42, "fp_ampl2": 1877.0, "std_noise": 20.0, "temperature": 50.36}
{"sample": null, "protocol": "", "distance": 0.52, "reference_point": ["0", "0.4", "0"], "timestamps": {"ts1": -1095148977.0, "ts2": -1787406407.0, "ts3": -1766653361.0, "ts4": -1074392966.0}, "rssi": -89.78, "fp_power": -88.86, "fp_ampl2": 1769.0, "std_noise": 28.0, "temperature": 50.36}
{"sample": null, "protocol": "", "distance": 0.58, "reference_point": ["0", "0.4", "0"], "timestamps": {"ts1": 149742159.0, "ts2": -528967041.0, "ts3": -508177329.0, "ts4": 170532781.0}, "rssi": -91.24, "fp_power": -88.12, "fp_ampl2": 1854.0, "std_noise": 20.0, "temperature": 50.36}
{"sample": null, "protocol": "", "distance": 0.62, "reference_point": ["0", "0.4", "0"], "timestamps": {"ts1": -1622830513.0, "ts2": 1980737059.0, "ts3": 2001641551.0, "ts4": -1601923036.0}, "rssi": -90.45, "fp_power": -87.09, "fp_ampl2": 2067.0, "std_noise": 24.0, "temperature": 50.36}
{"sample": null, "protocol": "", "distance": 0.62, "reference_point": ["0", "0.4", "0"], "timestamps": {"ts1": -377659313.0, "ts2": -1056225668.0, "ts3": -1035438513.0, "ts4": -356871243.0}, "rssi": -90.52, "fp_power": -87.44, "fp_ampl2": 2051.0, "std_noise": 24.0, "temperature": 50.36}
{"sample": null, "protocol": "", "distance": 0.58, "reference_point": ["0", "0.4", "0"], "timestamps": {"ts1": 2144554063.0, "ts2": 1454012106.0, "ts3": 1474772047.0, "ts4": -2129650321.0}, "rssi": -90.66, "fp_power": -88.0, "fp_ampl2": 2038.0, "std_noise": 24.0, "temperature": 50.36}
{"sample": null, "protocol": "", "distance": 0.62, "reference_point": ["0", "0.4", "0"], "timestamps": {"ts1": -905292721.0, "ts2": -1583716058.0, "ts3": -1562861489.0, "ts4": -884437259.0}, "rssi": -90.59, "fp_power": -88.24, "fp_ampl2": 1912.0, "std_noise": 24.0, "temperature": 50.36}
{"sample": null, "protocol": "", "distance": 0.57, "reference_point": ["0", "0.4", "0"], "timestamps": {"ts1": 1616924239.0, "ts2": 927240071.0, "ts3": 948059727.0, "ts4": 1637746880.0}, "rssi": -91.38, "fp_power": -87.6, "fp_ampl2": 2028.0, "std_noise": 20.0, "temperature": 49.22}
{"sample": null, "protocol": "", "distance": 0.59, "reference_point": ["0", "0.4", "0"], "timestamps": {"ts1": -1432617905.0, "ts2": -2110898111.0, "ts3": -2090113969.0, "ts4": -1411832859.0}, "rssi": -90.38, "fp_power": -87.34, "fp_ampl2": 1834.0, "std_noise": 24.0, "temperature": 50.36}
{"sample": null, "protocol": "", "distance": 0.59, "reference_point": ["0", "0.4", "0"], "timestamps": {"ts1": 1089389135.0, "ts2": 400562766.0, "ts3": 421316175.0, "ts4": 1110145531.0}, "rssi": -91.31, "fp_power": -87.0, "fp_ampl2": 2112.0, "std_noise": 20.0, "temperature": 50.36}
{"sample": null, "protocol": "", "distance": 0.57, "reference_point": ["0", "0.4", "0"], "timestamps": {"ts1": -1960102833.0, "ts2": 1656727451.0, "ts3": 1677600847.0, "ts4": -1939228535.0}, "rssi": -90.08, "fp_power": -87.01, "fp_ampl2": 1954.0, "std_noise": 24.0, "temperature": 50.36}
{"sample": null, "protocol": "", "distance": 0.56, "reference_point": ["0", "0.4", "0"], "timestamps": {"ts1": 561720911.0, "ts2": -126247642.0, "ts3": -105323953.0, "ts4": 582647599.0}, "rssi": -89.63, "fp_power": -89.16, "fp_ampl2": 1721.0, "std_noise": 28.0, "temperature": 50.36}
{"sample": null, "protocol": "", "distance": 0.57, "reference_point": ["0", "0.4", "0"], "timestamps": {"ts1": 1807179855.0, "ts2": 1129186043.0, "ts3": 1149943887.0, "ts4": 1827938594.0}, "rssi": -89.92, "fp_power": -86.67, "fp_ampl2": 2073.0, "std_noise": 28.0, "temperature": 49.22}
{"sample": null, "protocol": "", "distance": 0.6, "reference_point": ["0", "0.4", "0"], "timestamps": {"ts1": 34119759.0, "ts2": -652991017.0, "ts3": -632080305.0, "ts4": 55033458.0}, "rssi": -90.08, "fp_power": -87.24, "fp_ampl2": 1856.0, "std_noise": 24.0, "temperature": 50.36}
{"sample": null, "protocol": "", "distance": 0.56, "reference_point": ["0", "0.4", "0"], "timestamps": {"ts1": -486902193.0, "ts2": -1173499971.0, "ts3": -1152596401.0, "ts4": -465995657.0}, "rssi": -91.45, "fp_power": -86.49, "fp_ampl2": 2173.0, "std_noise": 20.0, "temperature": 50.36}
{"sample": null, "protocol": "", "distance": 0.6, "reference_point": ["0", "0.4", "0"], "timestamps": {"ts1": -493610929.0, "ts2": -1179863948.0, "ts3": -1159013297.0, "ts4": -472757289.0}, "rssi": -90.08, "fp_power": -88.0, "fp_ampl2": 1823.0, "std_noise": 24.0, "temperature": 50.36}
{"sample": null, "protocol": "", "distance": 0.57, "reference_point": ["0", "0.4", "0"], "timestamps": {"ts1": -1078508977.0, "ts2": -1764249508.0, "ts3": -1743400881.0, "ts4": -1057657369.0}, "rssi": -90.23, "fp_power": -86.95, "fp_ampl2": 2061.0, "std_noise": 24.0, "temperature": 50.36}
{"sample": null, "protocol": "", "distance": 0.59, "reference_point": ["0", "0.4", "0"], "timestamps": {"ts1": -1020983729.0, "ts2": -1706379011.0, "ts3": -1685559217.0, "ts4": -1000160982.0}, "rssi": -90.3, "fp_power": -87.12, "fp_ampl2": 2024.0, "std_noise": 24.0, "temperature": 49.22}
{"sample": null, "protocol": "", "distance": 0.58, "reference_point": ["0", "0.4", "0"], "timestamps": {"ts1": -1669900209.0, "ts2": 1940183783.0, "ts3": 1961076815.0, "ts4": -1649004192.0}, "rssi": -90.16, "fp_power": -86.71, "fp_ampl2": 2040.0, "std_noise": 24.0, "temperature": 50.36}
{"sample": null, "protocol": "", "distance": 0.62, "reference_point": ["0", "0.4", "0"], "timestamps": {"ts1": -1548588465.0, "ts2": 2061841300.0, "ts3": 2082779215.0, "ts4": -1527647581.0}, "rssi": -89.63, "fp_power": -88.91, "fp_ampl2": 1692.0, "std_noise": 28.0, "temperature": 50.36}
{"sample": null, "protocol": "", "distance": 0.56, "reference_point": ["0", "0.4", "0"], "timestamps": {"ts1": -302517169.0, "ts2": -979937987.0, "ts3": -959169969.0, "ts4": -281748250.0}, "rssi": -91.1, "fp_power": -86.97, "fp_ampl2": 1950.0, "std_noise": 20.0, "temperature": 49.22}
{"sample": null, "protocol": "", "distance": 0.55, "reference_point": ["0", "0.4", "0"], "timestamps": {"ts1": -2076279217.0, "ts2": 1535008264.0, "ts3": 1555857999.0, "ts4": -2055426512.0}, "rssi": -90.16, "fp_power": -87.18, "fp_ampl2": 1788.0, "std_noise": 24.0, "temperature": 50.36}
{"sample": null, "protocol": "", "distance": 0.56, "reference_point": ["0", "0.4", "0"], "timestamps": {"ts1": -1749944241.0, "ts2": 1861656140.0, "ts3": 1882455119.0, "ts4": -1729142286.0}, "rssi": -91.17, "fp_power": -87.92, "fp_ampl2": 1974.0, "std_noise": 20.0, "temperature": 50.36}
{"sample": null, "protocol": "", "distance": 0.58, "reference_point": ["0", "0.4", "0"], "timestamps": {"ts1": 1771675215.0, "ts2": 1088646869.0, "ts3": 1109397583.0, "ts4": 1792428923.0}, "rssi": -90.87, "fp_power": -87.38, "fp_ampl2": 1941.0, "std_noise": 20.0, "temperature": 50.36}
{"sample": null, "protocol": "", "distance": 0.56, "reference_point": ["0", "0.4", "0"], "timestamps": {"ts1": -1276912049.0, "ts2": -1954080840.0, "ts3": -1933167025.0, "ts4": -1255997315.0}, "rssi": -90.08, "fp_power": -86.47, "fp_ampl2": 2010.0, "std_noise": 24.0, "temperature": 50.36}
{"sample": null, "protocol": "", "distance": 0.61, "reference_point": ["0", "0.4", "0"], "timestamps": {"ts1": 1244235343.0, "ts2": 562064645.0, "ts3": 582569551.0, "ts4": 1264743226.0}, "rssi": -90.16, "fp_power": -87.13, "fp_ampl2": 1992.0, "std_noise": 24.0, "temperature": 50.36}
{"sample": null, "protocol": "", "distance": 0.58, "reference_point": ["0", "0.4", "0"], "timestamps": {"ts1": -1804598705.0, "ts2": 1813342977.0, "ts3": 1834109519.0, "ts4": -1783831259.0}, "rssi": -89.78, "fp_power": -88.12, "fp_ampl2": 1951.0, "std_noise": 28.0, "temperature": 50.36}
{"sample": null, "protocol": "", "distance": 0.58, "reference_point": ["0", "0.4", "0"], "timestamps": {"ts1": 716630607.0, "ts2": 35317557.0, "ts3": 56220751.0, "ts4": 737536802.0}, "rssi": -89.41, "fp_power": -86.75, "fp_ampl2": 1988.0, "std_noise": 28.0, "temperature": 49.22}
{"sample": null, "protocol": "", "distance": 0.54, "reference_point": ["0", "0.4", "0"], "timestamps": {"ts1": 1962920527.0, "ts2": 1286038030.0, "ts3": 1306840143.0, "ts4": 1983723538.0}, "rssi": -90.3, "fp_power": -86.32, "fp_ampl2": 2021.0, "std_noise": 24.0, "temperature": 50.36}
{"sample": null, "protocol": "", "distance": 0.55, "reference_point": ["0", "0.4", "0"], "timestamps": {"ts1": 188773455.0, "ts2": -491681994.0, "ts3": -470798769.0, "ts4": 209659673.0}, "rssi": -89.63, "fp_power": -88.35, "fp_ampl2": 1778.0, "std_noise": 28.0, "temperature": 50.36}
{"sample": null, "protocol": "", "distance": 0.58, "reference_point": ["0", "0.4", "0"], "timestamps": {"ts1": 179203663.0, "ts2": -500734782.0, "ts3": -479908273.0, "ts4": 200033166.0}, "rssi": -91.17, "fp_power": -86.82, "fp_ampl2": 1902.0, "std_noise": 20.0, "temperature": 50.36}
{"sample": null, "protocol": "", "distance": 0.54, "reference_point": ["0", "0.4", "0"], "timestamps": {"ts1": -402713009.0, "ts2": -1082311433.0, "ts3": -1061407665.0, "ts4": -381806285.0}, "rssi": -89.63, "fp_power": -86.85, "fp_ampl2": 1967.0, "std_noise": 28.0, "temperature": 49.22}
{"sample": null, "protocol": "", "distance": 0.57, "reference_point": ["0", "0.4", "0"], "timestamps": {"ts1": -1112084913.0, "ts2": -1791344303.0, "ts3": -1770451889.0, "ts4": -1091189525.0}, "rssi": -90.16, "fp_power": -87.05, "fp_ampl2": 1908.0, "std_noise": 24.0, "temperature": 50.36}
{"sample": null, "protocol": "", "distance": 0.59, "reference_point": ["0", "0.4", "0"], "timestamps": {"ts1": -993991089.0, "ts2": -1672732475.0, "ts3": -1651849137.0, "ts4": -973104768.0}, "rssi": -90.3, "fp_power": -87.41, "fp_ampl2": 1856.0, "std_noise": 24.0, "temperature": 50.36}
{"sample": null, "protocol": "", "distance": 0.56, "reference_point": ["0", "0.4", "0"], "timestamps": {"ts1": -1639797169.0, "ts2": 1976768247.0, "ts3": 1997557839.0, "ts4": -1619004613.0}, "rssi": -89.71, "fp_power": -87.85, "fp_ampl2": 1897.0, "std_noise": 28.0, "temperature": 50.36}
{"sample": null, "protocol": "", "distance": 0.6, "reference_point": ["0", "0.4", "0"], "timestamps": {"ts1": 1721562191.0, "ts2": 1043704323.0, "ts3": 1064524879.0, "ts4": 1742385710.0}, "rssi": -90.59, "fp_power": -90.84, "fp_ampl2": 1511.0, "std_noise": 24.0, "temperature": 50.36}
{"sample": null, "protocol": "", "distance": 0.57, "reference_point": ["0", "0.4", "0"], "timestamps": {"ts1": -1310600625.0, "ts2": -1986906450.0, "ts3": -1966267825.0, "ts4": -1289961088.0}, "rssi": -90.38, "fp_power": -89.36, "fp_ampl2": 1708.0, "std_noise": 24.0, "temperature": 50.36}
{"sample": null, "protocol": "", "distance": 0.59, "reference_point": ["0", "0.4", "0"], "timestamps": {"ts1": -1192717745.0, "ts2": -1868937099.0, "ts3": -1848056753.0, "ts4": -1171836499.0}, "rssi": -90.87, "fp_power": -88.28, "fp_ampl2": 1761.0, "std_noise": 20.0, "temperature": 50.36}
{"sample": null, "protocol": "", "distance": 0.58, "reference_point": ["0", "0.4", "0"], "timestamps": {"ts1": -1837991857.0, "ts2": 1780812763.0, "ts3": 1801725519.0, "ts4": -1817078199.0}, "rssi": -90.87, "fp_power": -88.34, "fp_ampl2": 1835.0, "std_noise": 20.0, "temperature": 50.36}
{"sample": null, "protocol": "", "distance": 0.54, "reference_point": ["0", "0.4", "0"], "timestamps": {"ts1": -771516337.0, "ts2": -1447429542.0, "ts3": -1426581425.0, "ts4": -750665252.0}, "rssi": -90.16, "fp_power": -88.28, "fp_ampl2": 1872.0, "std_noise": 24.0, "temperature": 50.36}
{"sample": null, "protocol": "", "distance": 0.52, "reference_point": ["0", "0.4", "0"], "timestamps": {"ts1": -1756265393.0, "ts2": 1863332258.0, "ts3": 1884184143.0, "ts4": -1735410524.0}, "rssi": -90.3, "fp_power": -87.06, "fp_ampl2": 2073.0, "std_noise": 24.0, "temperature": 50.36}
{"sample": null, "protocol": "", "distance": 5.14, "reference_point": ["0", "0.4", "0"], "timestamps": {"ts1": 236424271.0, "ts2": -438189234.0, "ts3": -417359793.0, "ts4": 257255954.0}, "rssi": -93.17, "fp_power": -104.63, "fp_ampl2": 128.0, "std_noise": 12.0, "temperature": 49.22}
